README.md
setup.py
lol_esports_parser/__init__.py
lol_esports_parser/config.py
lol_esports_parser/logger.py
lol_esports_parser.egg-info/PKG-INFO
lol_esports_parser.egg-info/SOURCES.txt
lol_esports_parser.egg-info/dependency_links.txt
lol_esports_parser.egg-info/requires.txt
lol_esports_parser.egg-info/top_level.txt
lol_esports_parser/dto/__init__.py
lol_esports_parser/dto/qq_source.py
lol_esports_parser/dto/series_dto.py
lol_esports_parser/dto/wp_dto.py
lol_esports_parser/parsers/__init__.py
lol_esports_parser/parsers/runes_handler.py
lol_esports_parser/parsers/qq/__init__.py
lol_esports_parser/parsers/qq/qq_access.py
lol_esports_parser/parsers/qq/qq_parser.py
lol_esports_parser/parsers/riot/__init__.py
lol_esports_parser/parsers/riot/acs_access.py
lol_esports_parser/parsers/riot/riot_parser.py
lol_esports_parser/parsers/wp/__init__.py
lol_esports_parser/parsers/wp/wp_access.py
lol_esports_parser/parsers/wp/wp_parser.py