Metadata-Version: 2.1
Name: lol-esports-parser
Version: 0.1a47
Summary: A utility to query and transform LoL games from QQ and ACS into the LolGame DTO format.
Home-page: https://github.com/mrtolkien/lol_esports_parser
Author: Gary "Tolki" Mialaret
Author-email: gary.mialaret+pypi@gmail.com
License: MIT
Platform: UNKNOWN
